cogent/__init__.py
cogent/align/__init__.py
cogent/align/_compare.so
cogent/align/_pairwise_pogs.so
cogent/align/_pairwise_seqs.so
cogent/align/algorithm.py
cogent/align/align.py
cogent/align/dp_calculation.py
cogent/align/indel_model.py
cogent/align/indel_positions.py
cogent/align/pairwise.py
cogent/align/progressive.py
cogent/align/pycompare.py
cogent/align/traceback.py
cogent/align/weights/__init__.py
cogent/align/weights/methods.py
cogent/align/weights/util.py
cogent/app/__init__.py
cogent/app/blast.py
cogent/app/blat.py
cogent/app/bwa.py
cogent/app/carnac.py
cogent/app/cd_hit.py
cogent/app/cdbfasta.py
cogent/app/clearcut.py
cogent/app/clustalw.py
cogent/app/cmfinder.py
cogent/app/comrna.py
cogent/app/consan.py
cogent/app/contrafold.py
cogent/app/cove.py
cogent/app/dialign.py
cogent/app/dotur.py
cogent/app/dynalign.py
cogent/app/fastq_join.py
cogent/app/fasttree.py
cogent/app/fasttree_v1.py
cogent/app/flash.py
cogent/app/foldalign.py
cogent/app/formatdb.py
cogent/app/gctmpca.py
cogent/app/guppy.py
cogent/app/ilm.py
cogent/app/infernal.py
cogent/app/knetfold.py
cogent/app/mafft.py
cogent/app/mfold.py
cogent/app/mothur.py
cogent/app/msms.py
cogent/app/muscle.py
cogent/app/muscle_v38.py
cogent/app/nupack.py
cogent/app/pandaseq.py
cogent/app/parameters.py
cogent/app/parsinsert.py
cogent/app/pfold.py
cogent/app/pknotsrg.py
cogent/app/pplacer.py
cogent/app/raxml.py
cogent/app/raxml_v730.py
cogent/app/rdp_classifier.py
cogent/app/rdp_classifier20.py
cogent/app/rnaalifold.py
cogent/app/rnaforester.py
cogent/app/rnashapes.py
cogent/app/rnaview.py
cogent/app/rtax.py
cogent/app/seqprep.py
cogent/app/sfffile.py
cogent/app/sffinfo.py
cogent/app/sfold.py
cogent/app/stride.py
cogent/app/uclust.py
cogent/app/unafold.py
cogent/app/usearch.py
cogent/app/util.py
cogent/app/vienna_package.py
cogent/cluster/UPGMA.py
cogent/cluster/__init__.py
cogent/cluster/approximate_mds.py
cogent-1.9.dist-info/DESCRIPTION.rst
cogent-1.9.dist-info/METADATA
cogent-1.9.dist-info/RECORD
cogent-1.9.dist-info/WHEEL
cogent-1.9.dist-info/metadata.json
cogent-1.9.dist-info/top_level.txt
