Metadata-Version: 2.0
Name: cogent
Version: 1.9
Summary: COmparative GENomics Toolkit
Home-page: http://github.com/pycogent/pycogent
Author: Gavin Huttley, Rob Knight
Author-email: gavin.huttley@anu.edu.au, rob@spot.colorado.edu
License: ['GPL']
Keywords: biology,genomics,statistics,phylogeny,evolution,bioinformatics
Platform: any
Classifier: Development Status :: 5 - Production/Stable
Classifier: Intended Audience :: Science/Research
Classifier: License :: OSI Approved :: GNU General Public License (GPL)
Classifier: Topic :: Scientific/Engineering :: Bio-Informatics
Classifier: Topic :: Software Development :: Libraries :: Python Modules
Classifier: Operating System :: OS Independent
Provides-Extra: all
Requires-Dist: PyMySQL; extra == 'all'
Requires-Dist: matplotlib; extra == 'all'
Requires-Dist: mpi4py; extra == 'all'
Requires-Dist: sqlalchemy; extra == 'all'
Provides-Extra: mpi
Requires-Dist: mpi4py; extra == 'mpi'
Provides-Extra: mysql
Requires-Dist: PyMySQL; extra == 'mysql'
Requires-Dist: sqlalchemy; extra == 'mysql'
